{
    "block0": [
        {
            "original_text": "Widely Recycled ",
            "translated_text": "Широко рециклиран"
        }
    ],
    "block1": [
        {
            "original_text": "57079 ",
            "translated_text": "Invalid Translation #000044"
        }
    ],
    "block2": [
        {
            "original_text": "Booker 000419 ",
            "translated_text": "Букър 000419"
        }
    ],
    "block3": [
        {
            "original_text": "Extra Large Tissues Average 100 Sheets x 2 - ply Tissue . Average Sheet Size 295mm x 275mm . Average Total Area 8.11m ? Happy Shopper Promise If you are not completely satisfied with our product please return it to the place of purchase , for a replacement or full refund . This does not affect your statutory rights Store in a cool , dry place . Produced in the UK . Happy Shopper , NN8 1LT , UK . ",
            "translated_text": "Изключително големи кърпички Средно 100 листа x 2-слойна кърпа. Среден размер на листа 295 мм x 275 мм. Средна обща площ 8.11m ? Happy Shopper Promise Ако не сте напълно доволни от нашия продукт, моля, върнете го на мястото на покупка, за замяна или пълно възстановяване на сумата. Това не засяга законовите ви права Съхранявайте на хладно и сухо място. Произведено в Обединеното кралство. Happy Shopper , NN8 1LT , UK ."
        }
    ],
    "block4": [
        {
            "original_text": "FSC ",
            "translated_text": "FSC"
        }
    ],
    "block5": [
        {
            "original_text": "MIX Paper from ",
            "translated_text": "MIX Хартия от"
        }
    ],
    "block6": [
        {
            "original_text": "FSC C074684 ",
            "translated_text": "FSC C074684"
        }
    ],
    "block7": [
        {
            "original_text": "5 \" 020379149303 > ",
            "translated_text": "Invalid Translation #000044"
        }
    ]
}